Metadata-Version: 1.0
Name: Amrrdistributions
Version: 0.1
Summary: Gaussian distributions
Home-page: https://github.com/amrrsalem
Author: Amrr
Author-email: amrr.salem@gmail.com
License: MIT
Platform: UNKNOWN
